quant/__init__.py
quant/analyze.py
quant/asset.py
quant/backtest.py
quant/collect.py
quant/config.py
quant/const.py
quant/datamatrix.py
quant/event.py
quant/gateway.py
quant/heartbeat.py
quant/history.py
quant/infra_api.py
quant/market.py
quant/order.py
quant/portfoliomanager.py
quant/position.py
quant/quant.py
quant/report.py
quant/startup.py
quant/state.py
quant/strategy.py
quant/tasks.py
quant/trader.py
quant/platform/__init__.py
quant/platform/ftx.py
quant/platform/huobi.py
quant/platform/huobi_future.py
quant/platform/okex.py
quant/utils/__init__.py
quant/utils/decorator.py
quant/utils/exceptions.py
quant/utils/http_client.py
quant/utils/logger.py
quant/utils/mongo.py
quant/utils/tools.py
quant/utils/websocket.py
alphahunterpro-0.9.1.dist-info/LICENSE
alphahunterpro-0.9.1.dist-info/LICENSE.txt
alphahunterpro-0.9.1.dist-info/METADATA
alphahunterpro-0.9.1.dist-info/WHEEL
alphahunterpro-0.9.1.dist-info/top_level.txt
alphahunterpro-0.9.1.dist-info/RECORD
