Metadata-Version: 2.1
Name: alphahunterpro
Version: 0.9.1
Summary: Asynchronous driven quantitative trading framework.
Home-page: https://github.com/yanjlee/alphahunter
Author: yanjlee
Author-email: 8342537@qq.com
License: MIT
Keywords: alphahunter,quant,framework,async,asynchronous,digiccy,digital,currency,marketmaker,binance,okex,huobi,bitmex,ftx
License-File: LICENSE
License-File: LICENSE.txt
Requires-Dist: requests
Requires-Dist: faker
Requires-Dist: execjs
Requires-Dist: loguru
Requires-Dist: base64
Requires-Dist: hashlib
Requires-Dist: Crypto
Requires-Dist: pandas
Requires-Dist: fuzzywuzzy
Requires-Dist: httpx
Requires-Dist: Pillow
Requires-Dist: playwright
Requires-Dist: PyExecJS
Requires-Dist: redis
Requires-Dist: fastapi
Requires-Dist: uvicorn
Requires-Dist: APScheduler
Requires-Dist: beautifulsoup4
Requires-Dist: bs4
Requires-Dist: certifi
Requires-Dist: clickhouse-driver
Requires-Dist: curl-cffi
Requires-Dist: DrissionPage
Requires-Dist: fake-useragent
Requires-Dist: Flask
Requires-Dist: Flask-APScheduler
Requires-Dist: Flask-Cors
Requires-Dist: frida
Requires-Dist: gevent
Requires-Dist: Jinja2
Requires-Dist: langchain
Requires-Dist: langchain-community
Requires-Dist: suiutils-py
Requires-Dist: 58
Requires-Dist: aiohttp ==3.2.1
Requires-Dist: aioamqp ==0.13.0
Requires-Dist: motor ==2.0.0
